{
  "$schema": "https://turborepo.com/schema.json",
  "ui": "tui",
  "tasks": {
    "build": {
      "dependsOn": ["^build"],
      "outputs": ["dist/**"]
    },
    "dev": {
      "cache": false,
      "persistent": true
    },
    "check-types": {
      "dependsOn": ["^build"]
    },
    "format": {
      "cache": false
    },
    "lint": {
      "dependsOn": ["^build"]
    },
    "test": {
      "dependsOn": ["^build"]
    },
    "test:e2e": {
      "dependsOn": ["^build"],
      "cache": false
    },
    "check": {
      "dependsOn": ["^build"],
      "cache": false
    }
  }
}
